{
  "success": true,
  "schema_version": 1,
  "artifact_kind": "moza_vendor_authority_attempt",
  "claim_scope": "bounded_vendor_authority_attempt_recorded",
  "command": "wheelctl moza vendor-authority-attempt",
  "generated_at_utc": "2026-05-20T20:46:23Z",
  "authorization_receipt": "ci\\hardware\\moza-r5\\2026-05-13\\vendor-authority-authorization.json",
  "smoke_dry_run_receipt": "ci\\hardware\\moza-r5\\2026-05-13\\vendor-authority-smoke-dry-run.json",
  "authorization_receipt_validated": true,
  "smoke_dry_run_receipt_validated": true,
  "authorization_consumed": true,
  "exact_authorization": true,
  "single_use_authorization": true,
  "native_control_evidence": false,
  "hardware_output_authorized": false,
  "native_visible_ready": false,
  "smoke_ready": false,
  "next_allowed_action": "Record post-authority PIDFF response comparison before any motion claim.",
  "blocked_actions": [
    "authorization reuse",
    "second send from this receipt",
    "native-visible promotion",
    "smoke-ready promotion",
    "release-ready promotion",
    "firmware or DFU command",
    "unknown host-to-device command",
    "direct HID report 0xaf",
    "high-torque enablement"
  ],
  "required_artifacts": [
    "docs/specs/OR-SPEC-0002-moza-r5-vendor-authority-test-lane.md",
    "docs/hardware/moza-r5-vendor-authority-test-plan.md",
    "schemas/moza-vendor-authority-authorization.schema.json",
    "schemas/moza-vendor-authority-smoke.schema.json",
    "schemas/moza-vendor-authority-attempt.schema.json",
    "crates/cli/src/commands/moza.rs"
  ],
  "serial_port": "COM4",
  "baud_rate": 115200,
  "timeout_ms": 250,
  "expected_vid": "0x346E",
  "expected_pid": "0x0004",
  "port_identity": {
    "port_name": "COM4",
    "port_type": "usb",
    "vendor_id": "0x346E",
    "product_id": "0x0004",
    "manufacturer": "Microsoft",
    "product": "USB Serial Device (COM4)",
    "serial_number_present": true
  },
  "serial_identity_verified": true,
  "no_hid_device_opened": true,
  "opened_serial_device": true,
  "sent_read_only_query_commands": false,
  "sent_authorized_frame": true,
  "sent_authorized_frame_count": 1,
  "sent_output_writes": true,
  "sent_configuration_writes": false,
  "sent_firmware_or_dfu_commands": false,
  "sent_unknown_commands": false,
  "direct_hid_report_0xaf_sent": false,
  "high_torque_enabled": false,
  "transport_kind": "serial_bounded_authority_attempt",
  "codec_status": "fixture_decode_verified_exact_frame",
  "hardware_write_eligible": false,
  "authorized_command": {
    "command_id": "estop_set_ffb",
    "command_name": "EstopCtrl_SetFfb",
    "family": "authority_state",
    "group": 70,
    "device_id": 28,
    "command": 0,
    "risk_class": "vendor_output_candidate",
    "read_only_status_probe_allowed": false
  },
  "authorized_frame": {
    "frame_hex": "7E02461C0001F0",
    "frame_sha256": "5ceac21f0e50faf287404178143f03abdea04acdc10c0d935f8dfb11b939dffe",
    "frame_len": 7,
    "payload_hex": "01",
    "payload_sha256": "4bf5122f344554c53bde2ebb8cd2b7e3d1600ad631c385a5d7cce23c7785459a",
    "payload_len": 1,
    "checksum": "0xF0",
    "written_frame_sha256": "5ceac21f0e50faf287404178143f03abdea04acdc10c0d935f8dfb11b939dffe",
    "written_frame_len": 7
  },
  "authorization_consumption": {
    "consumption_recorded": true,
    "authorization_reuse_allowed": false,
    "requires_new_bench_clear_for_retry": true,
    "requires_new_authorization_for_retry": true,
    "requires_new_smoke_dry_run_for_retry": true,
    "requires_new_attempt_receipt_for_retry": true
  },
  "planned_next_output": {
    "allowed": false,
    "reason": "The first authority attempt is consumed evidence, not reusable authorization."
  },
  "notes": [
    "This receipt records one exact vendor-authority frame send through the serial interface.",
    "It consumes the matching authorization and does not authorize retry or promotion.",
    "It is not native-control, native-visible, smoke-ready, coexistence, simulator, or release-ready proof."
  ]
}